lyrebird_android/__init__.py
lyrebird_android/android_helper.py
lyrebird_android/config.py
lyrebird_android/device_service.py
lyrebird_android/ui.py
lyrebird_android/static/vue-resource.js
lyrebird_android/static/vue.js
lyrebird_android/templates/index.html
lyrebird_android-0.1.11.dist-info/METADATA
lyrebird_android-0.1.11.dist-info/RECORD
lyrebird_android-0.1.11.dist-info/WHEEL
lyrebird_android-0.1.11.dist-info/entry_points.txt
lyrebird_android-0.1.11.dist-info/top_level.txt
