Metadata-Version: 2.1
Name: lyrebird-android
Version: 0.1.11
Summary: UNKNOWN
Home-page: https://github.com/meituan/lyrebird-android
Author: HBQA
Author-email: 
License: UNKNOWN
Platform: UNKNOWN
Classifier: Programming Language :: Python :: 3 :: Only
Classifier: Programming Language :: Python :: 3.6
Classifier: License :: OSI Approved :: MIT License
Classifier: Operating System :: MacOS
Requires-Dist: lyrebird
